{
    "/js//main.min.js": "/js//main.min.js",
    "/images/photo-wide-4.jpg?ea98fbfd3510c4f272ebf0b557fc7eba": "/images/photo-wide-4.jpg?ea98fbfd3510c4f272ebf0b557fc7eba",
    "/images/page-bg-bottom.png?83e9c72af45681bac04ea0d922febd71": "/images/page-bg-bottom.png?83e9c72af45681bac04ea0d922febd71",
    "/images/photo-wide-5.jpeg?6c1e776a6d7279764999a21fcb444563": "/images/photo-wide-5.jpeg?6c1e776a6d7279764999a21fcb444563",
    "/fonts/icomoon.eot?6a6f7bd187c115ac4928375f88afe630": "/fonts/icomoon.eot?6a6f7bd187c115ac4928375f88afe630",
    "/fonts/icomoon.woff?beb5072df50c81b5d0f77916e825bd01": "/fonts/icomoon.woff?beb5072df50c81b5d0f77916e825bd01",
    "/fonts/icomoon.ttf?da51bee3e2032af85b1529aa3af3fa36": "/fonts/icomoon.ttf?da51bee3e2032af85b1529aa3af3fa36",
    "/js//login.min.js": "/js//login.min.js",
    "/js//customer-display.min.js": "/js//customer-display.min.js",
    "/js/bundle/dashboard.1db6ca7d2caaa5e3.js": "/js/bundle/dashboard.1db6ca7d2caaa5e3.js",
    "/js/bundle/products.1db6ca7d2caaa5e3.js": "/js/bundle/products.1db6ca7d2caaa5e3.js",
    "/js/bundle/index_products.1db6ca7d2caaa5e3.js": "/js/bundle/index_products.1db6ca7d2caaa5e3.js",
    "/js/bundle/import_products.1db6ca7d2caaa5e3.js": "/js/bundle/import_products.1db6ca7d2caaa5e3.js",
    "/js/bundle/store_product.1db6ca7d2caaa5e3.js": "/js/bundle/store_product.1db6ca7d2caaa5e3.js",
    "/js/bundle/edit_product.1db6ca7d2caaa5e3.js": "/js/bundle/edit_product.1db6ca7d2caaa5e3.js",
    "/js/bundle/detail_product.1db6ca7d2caaa5e3.js": "/js/bundle/detail_product.1db6ca7d2caaa5e3.js",
    "/js/bundle/opening_stock_import.1db6ca7d2caaa5e3.js": "/js/bundle/opening_stock_import.1db6ca7d2caaa5e3.js",
    "/js/bundle/barcode.1db6ca7d2caaa5e3.js": "/js/bundle/barcode.1db6ca7d2caaa5e3.js",
    "/js/bundle/count_stock.1db6ca7d2caaa5e3.js": "/js/bundle/count_stock.1db6ca7d2caaa5e3.js",
    "/js/bundle/Categories.1db6ca7d2caaa5e3.js": "/js/bundle/Categories.1db6ca7d2caaa5e3.js",
    "/fonts/vendor/bootstrap-icons/bootstrap-icons.woff2?92ea18a81d737146ff044ddb52010366": "/fonts/vendor/bootstrap-icons/bootstrap-icons.woff2?92ea18a81d737146ff044ddb52010366",
    "/fonts/vendor/bootstrap-icons/bootstrap-icons.woff?1295669cd4e305c97f2cfc16d56614b8": "/fonts/vendor/bootstrap-icons/bootstrap-icons.woff?1295669cd4e305c97f2cfc16d56614b8",
    "/js/bundle/SubCategories.1db6ca7d2caaa5e3.js": "/js/bundle/SubCategories.1db6ca7d2caaa5e3.js",
    "/js/bundle/Brands.1db6ca7d2caaa5e3.js": "/js/bundle/Brands.1db6ca7d2caaa5e3.js",
    "/js/bundle/units.1db6ca7d2caaa5e3.js": "/js/bundle/units.1db6ca7d2caaa5e3.js",
    "/js/bundle/adjustments.1db6ca7d2caaa5e3.js": "/js/bundle/adjustments.1db6ca7d2caaa5e3.js",
    "/js/bundle/index_adjustment.1db6ca7d2caaa5e3.js": "/js/bundle/index_adjustment.1db6ca7d2caaa5e3.js",
    "/js/bundle/store_adjustment.1db6ca7d2caaa5e3.js": "/js/bundle/store_adjustment.1db6ca7d2caaa5e3.js",
    "/js/bundle/edit_adjustment.1db6ca7d2caaa5e3.js": "/js/bundle/edit_adjustment.1db6ca7d2caaa5e3.js",
    "/js/bundle/damages.1db6ca7d2caaa5e3.js": "/js/bundle/damages.1db6ca7d2caaa5e3.js",
    "/js/bundle/index_damage.1db6ca7d2caaa5e3.js": "/js/bundle/index_damage.1db6ca7d2caaa5e3.js",
    "/js/bundle/store_damage.1db6ca7d2caaa5e3.js": "/js/bundle/store_damage.1db6ca7d2caaa5e3.js",
    "/js/bundle/edit_damage.1db6ca7d2caaa5e3.js": "/js/bundle/edit_damage.1db6ca7d2caaa5e3.js",
    "/js/bundle/transfers.1db6ca7d2caaa5e3.js": "/js/bundle/transfers.1db6ca7d2caaa5e3.js",
    "/js/bundle/index_transfer.1db6ca7d2caaa5e3.js": "/js/bundle/index_transfer.1db6ca7d2caaa5e3.js",
    "/js/bundle/store_transfer.1db6ca7d2caaa5e3.js": "/js/bundle/store_transfer.1db6ca7d2caaa5e3.js",
    "/js/bundle/edit_transfer.1db6ca7d2caaa5e3.js": "/js/bundle/edit_transfer.1db6ca7d2caaa5e3.js",
    "/js/bundle/detail_transfer.1db6ca7d2caaa5e3.js": "/js/bundle/detail_transfer.1db6ca7d2caaa5e3.js",
    "/js/bundle/accounts.1db6ca7d2caaa5e3.js": "/js/bundle/accounts.1db6ca7d2caaa5e3.js",
    "/js/bundle/projects.1db6ca7d2caaa5e3.js": "/js/bundle/projects.1db6ca7d2caaa5e3.js",
    "/js/bundle/index_project.1db6ca7d2caaa5e3.js": "/js/bundle/index_project.1db6ca7d2caaa5e3.js",
    "/js/bundle/store_project.1db6ca7d2caaa5e3.js": "/js/bundle/store_project.1db6ca7d2caaa5e3.js",
    "/js/bundle/edit_project.1db6ca7d2caaa5e3.js": "/js/bundle/edit_project.1db6ca7d2caaa5e3.js",
    "/js/bundle/tasks.1db6ca7d2caaa5e3.js": "/js/bundle/tasks.1db6ca7d2caaa5e3.js",
    "/js/bundle/index_task.1db6ca7d2caaa5e3.js": "/js/bundle/index_task.1db6ca7d2caaa5e3.js",
    "/js/bundle/store_task.1db6ca7d2caaa5e3.js": "/js/bundle/store_task.1db6ca7d2caaa5e3.js",
    "/js/bundle/edit_task.1db6ca7d2caaa5e3.js": "/js/bundle/edit_task.1db6ca7d2caaa5e3.js",
    "/js/bundle/bookings.1db6ca7d2caaa5e3.js": "/js/bundle/bookings.1db6ca7d2caaa5e3.js",
    "/js/bundle/index_booking.1db6ca7d2caaa5e3.js": "/js/bundle/index_booking.1db6ca7d2caaa5e3.js",
    "/js/bundle/store_booking.1db6ca7d2caaa5e3.js": "/js/bundle/store_booking.1db6ca7d2caaa5e3.js",
    "/js/bundle/edit_booking.1db6ca7d2caaa5e3.js": "/js/bundle/edit_booking.1db6ca7d2caaa5e3.js",
    "/js/bundle/calendar_booking.1db6ca7d2caaa5e3.js": "/js/bundle/calendar_booking.1db6ca7d2caaa5e3.js",
    "/js/bundle/assets.1db6ca7d2caaa5e3.js": "/js/bundle/assets.1db6ca7d2caaa5e3.js",
    "/js/bundle/index_asset.1db6ca7d2caaa5e3.js": "/js/bundle/index_asset.1db6ca7d2caaa5e3.js",
    "/js/bundle/store_asset.1db6ca7d2caaa5e3.js": "/js/bundle/store_asset.1db6ca7d2caaa5e3.js",
    "/js/bundle/edit_asset.1db6ca7d2caaa5e3.js": "/js/bundle/edit_asset.1db6ca7d2caaa5e3.js",
    "/js/bundle/asset_category.1db6ca7d2caaa5e3.js": "/js/bundle/asset_category.1db6ca7d2caaa5e3.js",
    "/js/bundle/service.1db6ca7d2caaa5e3.js": "/js/bundle/service.1db6ca7d2caaa5e3.js",
    "/js/bundle/service_jobs_index.1db6ca7d2caaa5e3.js": "/js/bundle/service_jobs_index.1db6ca7d2caaa5e3.js",
    "/js/bundle/service_job_edit.1db6ca7d2caaa5e3.js": "/js/bundle/service_job_edit.1db6ca7d2caaa5e3.js",
    "/js/bundle/service_job_details.1db6ca7d2caaa5e3.js": "/js/bundle/service_job_details.1db6ca7d2caaa5e3.js",
    "/js/bundle/service_checklist_categories.1db6ca7d2caaa5e3.js": "/js/bundle/service_checklist_categories.1db6ca7d2caaa5e3.js",
    "/js/bundle/service_checklists.1db6ca7d2caaa5e3.js": "/js/bundle/service_checklists.1db6ca7d2caaa5e3.js",
    "/js/bundle/service_technicians.1db6ca7d2caaa5e3.js": "/js/bundle/service_technicians.1db6ca7d2caaa5e3.js",
    "/js/bundle/customer_maintenance_history.1db6ca7d2caaa5e3.js": "/js/bundle/customer_maintenance_history.1db6ca7d2caaa5e3.js",
    "/js/bundle/transfer_money.1db6ca7d2caaa5e3.js": "/js/bundle/transfer_money.1db6ca7d2caaa5e3.js",
    "/js/bundle/expenses.1db6ca7d2caaa5e3.js": "/js/bundle/expenses.1db6ca7d2caaa5e3.js",
    "/js/bundle/index_expense.1db6ca7d2caaa5e3.js": "/js/bundle/index_expense.1db6ca7d2caaa5e3.js",
    "/js/bundle/store_expense.1db6ca7d2caaa5e3.js": "/js/bundle/store_expense.1db6ca7d2caaa5e3.js",
    "/js/bundle/edit_expense.1db6ca7d2caaa5e3.js": "/js/bundle/edit_expense.1db6ca7d2caaa5e3.js",
    "/js/bundle/expense_category.1db6ca7d2caaa5e3.js": "/js/bundle/expense_category.1db6ca7d2caaa5e3.js",
    "/js/bundle/deposits.1db6ca7d2caaa5e3.js": "/js/bundle/deposits.1db6ca7d2caaa5e3.js",
    "/js/bundle/index_deposit.1db6ca7d2caaa5e3.js": "/js/bundle/index_deposit.1db6ca7d2caaa5e3.js",
    "/js/bundle/store_deposit.1db6ca7d2caaa5e3.js": "/js/bundle/store_deposit.1db6ca7d2caaa5e3.js",
    "/js/bundle/edit_deposit.1db6ca7d2caaa5e3.js": "/js/bundle/edit_deposit.1db6ca7d2caaa5e3.js",
    "/js/bundle/deposit_category.1db6ca7d2caaa5e3.js": "/js/bundle/deposit_category.1db6ca7d2caaa5e3.js",
    "/js/bundle/quotations.1db6ca7d2caaa5e3.js": "/js/bundle/quotations.1db6ca7d2caaa5e3.js",
    "/js/bundle/store_quotation.1db6ca7d2caaa5e3.js": "/js/bundle/store_quotation.1db6ca7d2caaa5e3.js",
    "/js/bundle/edit_quotation.1db6ca7d2caaa5e3.js": "/js/bundle/edit_quotation.1db6ca7d2caaa5e3.js",
    "/js/bundle/detail_quotation.1db6ca7d2caaa5e3.js": "/js/bundle/detail_quotation.1db6ca7d2caaa5e3.js",
    "/js/bundle/change_to_sale.1db6ca7d2caaa5e3.js": "/js/bundle/change_to_sale.1db6ca7d2caaa5e3.js",
    "/js/bundle/accounting_v2.1db6ca7d2caaa5e3.js": "/js/bundle/accounting_v2.1db6ca7d2caaa5e3.js",
    "/js/bundle/accounting_v2_dashboard.1db6ca7d2caaa5e3.js": "/js/bundle/accounting_v2_dashboard.1db6ca7d2caaa5e3.js",
    "/js/bundle/accounting_v2_chart_of_accounts.1db6ca7d2caaa5e3.js": "/js/bundle/accounting_v2_chart_of_accounts.1db6ca7d2caaa5e3.js",
    "/js/bundle/accounting_v2_journal_entries.1db6ca7d2caaa5e3.js": "/js/bundle/accounting_v2_journal_entries.1db6ca7d2caaa5e3.js",
    "/js/bundle/accounting_v2_trial_balance.1db6ca7d2caaa5e3.js": "/js/bundle/accounting_v2_trial_balance.1db6ca7d2caaa5e3.js",
    "/js/bundle/accounting_v2_profit_loss.1db6ca7d2caaa5e3.js": "/js/bundle/accounting_v2_profit_loss.1db6ca7d2caaa5e3.js",
    "/js/bundle/accounting_v2_balance_sheet.1db6ca7d2caaa5e3.js": "/js/bundle/accounting_v2_balance_sheet.1db6ca7d2caaa5e3.js",
    "/js/bundle/accounting_v2_tax_report.1db6ca7d2caaa5e3.js": "/js/bundle/accounting_v2_tax_report.1db6ca7d2caaa5e3.js",
    "/js/bundle/customer_display_setup.1db6ca7d2caaa5e3.js": "/js/bundle/customer_display_setup.1db6ca7d2caaa5e3.js",
    "/js/bundle/purchases.1db6ca7d2caaa5e3.js": "/js/bundle/purchases.1db6ca7d2caaa5e3.js",
    "/js/bundle/index_purchases.1db6ca7d2caaa5e3.js": "/js/bundle/index_purchases.1db6ca7d2caaa5e3.js",
    "/js/bundle/store_purchase.1db6ca7d2caaa5e3.js": "/js/bundle/store_purchase.1db6ca7d2caaa5e3.js",
    "/js/bundle/import_purchases.1db6ca7d2caaa5e3.js": "/js/bundle/import_purchases.1db6ca7d2caaa5e3.js",
    "/js/bundle/edit_purchase.1db6ca7d2caaa5e3.js": "/js/bundle/edit_purchase.1db6ca7d2caaa5e3.js",
    "/js/bundle/create_purchase_return.1db6ca7d2caaa5e3.js": "/js/bundle/create_purchase_return.1db6ca7d2caaa5e3.js",
    "/js/bundle/detail_purchase.1db6ca7d2caaa5e3.js": "/js/bundle/detail_purchase.1db6ca7d2caaa5e3.js",
    "/js/bundle/sales.1db6ca7d2caaa5e3.js": "/js/bundle/sales.1db6ca7d2caaa5e3.js",
    "/js/bundle/index_sales.1db6ca7d2caaa5e3.js": "/js/bundle/index_sales.1db6ca7d2caaa5e3.js",
    "/js/bundle/store_sale.1db6ca7d2caaa5e3.js": "/js/bundle/store_sale.1db6ca7d2caaa5e3.js",
    "/js/bundle/edit_sale.1db6ca7d2caaa5e3.js": "/js/bundle/edit_sale.1db6ca7d2caaa5e3.js",
    "/js/bundle/create_sale_return.1db6ca7d2caaa5e3.js": "/js/bundle/create_sale_return.1db6ca7d2caaa5e3.js",
    "/js/bundle/detail_sale.1db6ca7d2caaa5e3.js": "/js/bundle/detail_sale.1db6ca7d2caaa5e3.js",
    "/js/bundle/shipment.1db6ca7d2caaa5e3.js": "/js/bundle/shipment.1db6ca7d2caaa5e3.js",
    "/js/bundle/sale_return.1db6ca7d2caaa5e3.js": "/js/bundle/sale_return.1db6ca7d2caaa5e3.js",
    "/js/bundle/index_sale_return.1db6ca7d2caaa5e3.js": "/js/bundle/index_sale_return.1db6ca7d2caaa5e3.js",
    "/js/bundle/edit_sale_return.1db6ca7d2caaa5e3.js": "/js/bundle/edit_sale_return.1db6ca7d2caaa5e3.js",
    "/js/bundle/detail_sale_return.1db6ca7d2caaa5e3.js": "/js/bundle/detail_sale_return.1db6ca7d2caaa5e3.js",
    "/js/bundle/purchase_return.1db6ca7d2caaa5e3.js": "/js/bundle/purchase_return.1db6ca7d2caaa5e3.js",
    "/js/bundle/index_purchase_return.1db6ca7d2caaa5e3.js": "/js/bundle/index_purchase_return.1db6ca7d2caaa5e3.js",
    "/js/bundle/edit_purchase_return.1db6ca7d2caaa5e3.js": "/js/bundle/edit_purchase_return.1db6ca7d2caaa5e3.js",
    "/js/bundle/detail_purchase_return.1db6ca7d2caaa5e3.js": "/js/bundle/detail_purchase_return.1db6ca7d2caaa5e3.js",
    "/js/bundle/hrm.1db6ca7d2caaa5e3.js": "/js/bundle/hrm.1db6ca7d2caaa5e3.js",
    "/js/bundle/employees.1db6ca7d2caaa5e3.js": "/js/bundle/employees.1db6ca7d2caaa5e3.js",
    "/js/bundle/index_employee.1db6ca7d2caaa5e3.js": "/js/bundle/index_employee.1db6ca7d2caaa5e3.js",
    "/js/bundle/store_employee.1db6ca7d2caaa5e3.js": "/js/bundle/store_employee.1db6ca7d2caaa5e3.js",
    "/js/bundle/edit_employee.1db6ca7d2caaa5e3.js": "/js/bundle/edit_employee.1db6ca7d2caaa5e3.js",
    "/js/bundle/detail_employee.1db6ca7d2caaa5e3.js": "/js/bundle/detail_employee.1db6ca7d2caaa5e3.js",
    "/js/bundle/company.1db6ca7d2caaa5e3.js": "/js/bundle/company.1db6ca7d2caaa5e3.js",
    "/js/bundle/departments.1db6ca7d2caaa5e3.js": "/js/bundle/departments.1db6ca7d2caaa5e3.js",
    "/js/bundle/designations.1db6ca7d2caaa5e3.js": "/js/bundle/designations.1db6ca7d2caaa5e3.js",
    "/js/bundle/office_shift.1db6ca7d2caaa5e3.js": "/js/bundle/office_shift.1db6ca7d2caaa5e3.js",
    "/js/bundle/attendance.1db6ca7d2caaa5e3.js": "/js/bundle/attendance.1db6ca7d2caaa5e3.js",
    "/js/bundle/holidays.1db6ca7d2caaa5e3.js": "/js/bundle/holidays.1db6ca7d2caaa5e3.js",
    "/js/bundle/payrolls.1db6ca7d2caaa5e3.js": "/js/bundle/payrolls.1db6ca7d2caaa5e3.js",
    "/js/bundle/leaves.1db6ca7d2caaa5e3.js": "/js/bundle/leaves.1db6ca7d2caaa5e3.js",
    "/js/bundle/leave_list.1db6ca7d2caaa5e3.js": "/js/bundle/leave_list.1db6ca7d2caaa5e3.js",
    "/js/bundle/leave_type.1db6ca7d2caaa5e3.js": "/js/bundle/leave_type.1db6ca7d2caaa5e3.js",
    "/js/bundle/Store.1db6ca7d2caaa5e3.js": "/js/bundle/Store.1db6ca7d2caaa5e3.js",
    "/js/bundle/StoreSettings.1db6ca7d2caaa5e3.js": "/js/bundle/StoreSettings.1db6ca7d2caaa5e3.js",
    "/js/bundle/StoreOrders.1db6ca7d2caaa5e3.js": "/js/bundle/StoreOrders.1db6ca7d2caaa5e3.js",
    "/js/bundle/StoreOrderShow.1db6ca7d2caaa5e3.js": "/js/bundle/StoreOrderShow.1db6ca7d2caaa5e3.js",
    "/js/bundle/CollectionsIndex.1db6ca7d2caaa5e3.js": "/js/bundle/CollectionsIndex.1db6ca7d2caaa5e3.js",
    "/js/bundle/CollectionsCreate.1db6ca7d2caaa5e3.js": "/js/bundle/CollectionsCreate.1db6ca7d2caaa5e3.js",
    "/js/bundle/CollectionsEdit.1db6ca7d2caaa5e3.js": "/js/bundle/CollectionsEdit.1db6ca7d2caaa5e3.js",
    "/js/bundle/StoreSubscribers.1db6ca7d2caaa5e3.js": "/js/bundle/StoreSubscribers.1db6ca7d2caaa5e3.js",
    "/js/bundle/StoreMessages.1db6ca7d2caaa5e3.js": "/js/bundle/StoreMessages.1db6ca7d2caaa5e3.js",
    "/js/bundle/StoreBanners.1db6ca7d2caaa5e3.js": "/js/bundle/StoreBanners.1db6ca7d2caaa5e3.js",
    "/js/bundle/StoreBannerEdit.1db6ca7d2caaa5e3.js": "/js/bundle/StoreBannerEdit.1db6ca7d2caaa5e3.js",
    "/js/bundle/People.1db6ca7d2caaa5e3.js": "/js/bundle/People.1db6ca7d2caaa5e3.js",
    "/js/bundle/Customers.1db6ca7d2caaa5e3.js": "/js/bundle/Customers.1db6ca7d2caaa5e3.js",
    "/js/bundle/Create_Customer.1db6ca7d2caaa5e3.js": "/js/bundle/Create_Customer.1db6ca7d2caaa5e3.js",
    "/js/bundle/Edit_Customer.1db6ca7d2caaa5e3.js": "/js/bundle/Edit_Customer.1db6ca7d2caaa5e3.js",
    "/js/bundle/Import_Customers.1db6ca7d2caaa5e3.js": "/js/bundle/Import_Customers.1db6ca7d2caaa5e3.js",
    "/js/bundle/CustomerLedger.1db6ca7d2caaa5e3.js": "/js/bundle/CustomerLedger.1db6ca7d2caaa5e3.js",
    "/js/bundle/CustomerDetails.1db6ca7d2caaa5e3.js": "/js/bundle/CustomerDetails.1db6ca7d2caaa5e3.js",
    "/js/bundle/Customers_without_ecommerce.1db6ca7d2caaa5e3.js": "/js/bundle/Customers_without_ecommerce.1db6ca7d2caaa5e3.js",
    "/js/bundle/Customers_ecommerce.1db6ca7d2caaa5e3.js": "/js/bundle/Customers_ecommerce.1db6ca7d2caaa5e3.js",
    "/js/bundle/Suppliers.1db6ca7d2caaa5e3.js": "/js/bundle/Suppliers.1db6ca7d2caaa5e3.js",
    "/js/bundle/Create_Supplier.1db6ca7d2caaa5e3.js": "/js/bundle/Create_Supplier.1db6ca7d2caaa5e3.js",
    "/js/bundle/Edit_Supplier.1db6ca7d2caaa5e3.js": "/js/bundle/Edit_Supplier.1db6ca7d2caaa5e3.js",
    "/js/bundle/Import_Suppliers.1db6ca7d2caaa5e3.js": "/js/bundle/Import_Suppliers.1db6ca7d2caaa5e3.js",
    "/js/bundle/User_Management.1db6ca7d2caaa5e3.js": "/js/bundle/User_Management.1db6ca7d2caaa5e3.js",
    "/js/bundle/Users.1db6ca7d2caaa5e3.js": "/js/bundle/Users.1db6ca7d2caaa5e3.js",
    "/js/bundle/Create_User.1db6ca7d2caaa5e3.js": "/js/bundle/Create_User.1db6ca7d2caaa5e3.js",
    "/js/bundle/Edit_User.1db6ca7d2caaa5e3.js": "/js/bundle/Edit_User.1db6ca7d2caaa5e3.js",
    "/js/bundle/permissions.1db6ca7d2caaa5e3.js": "/js/bundle/permissions.1db6ca7d2caaa5e3.js",
    "/js/bundle/groupPermission.1db6ca7d2caaa5e3.js": "/js/bundle/groupPermission.1db6ca7d2caaa5e3.js",
    "/js/bundle/store_permission.1db6ca7d2caaa5e3.js": "/js/bundle/store_permission.1db6ca7d2caaa5e3.js",
    "/js/bundle/edit_permission.1db6ca7d2caaa5e3.js": "/js/bundle/edit_permission.1db6ca7d2caaa5e3.js",
    "/js/bundle/subscription_product.1db6ca7d2caaa5e3.js": "/js/bundle/subscription_product.1db6ca7d2caaa5e3.js",
    "/js/bundle/subscription_product_create.1db6ca7d2caaa5e3.js": "/js/bundle/subscription_product_create.1db6ca7d2caaa5e3.js",
    "/js/bundle/subscription_product_details.1db6ca7d2caaa5e3.js": "/js/bundle/subscription_product_details.1db6ca7d2caaa5e3.js",
    "/js/bundle/settings.1db6ca7d2caaa5e3.js": "/js/bundle/settings.1db6ca7d2caaa5e3.js",
    "/js/bundle/payment_methods.1db6ca7d2caaa5e3.js": "/js/bundle/payment_methods.1db6ca7d2caaa5e3.js",
    "/js/bundle/sms_settings.1db6ca7d2caaa5e3.js": "/js/bundle/sms_settings.1db6ca7d2caaa5e3.js",
    "/js/bundle/quickbooks_sync.1db6ca7d2caaa5e3.js": "/js/bundle/quickbooks_sync.1db6ca7d2caaa5e3.js",
    "/js/bundle/sms_templates.1db6ca7d2caaa5e3.js": "/js/bundle/sms_templates.1db6ca7d2caaa5e3.js",
    "/js/bundle/email_templates.1db6ca7d2caaa5e3.js": "/js/bundle/email_templates.1db6ca7d2caaa5e3.js",
    "/js/bundle/appearance_settings.1db6ca7d2caaa5e3.js": "/js/bundle/appearance_settings.1db6ca7d2caaa5e3.js",
    "/js/bundle/translations_settings.1db6ca7d2caaa5e3.js": "/js/bundle/translations_settings.1db6ca7d2caaa5e3.js",
    "/js/bundle/translations_view.1db6ca7d2caaa5e3.js": "/js/bundle/translations_view.1db6ca7d2caaa5e3.js",
    "/js/bundle/pos_settings.1db6ca7d2caaa5e3.js": "/js/bundle/pos_settings.1db6ca7d2caaa5e3.js",
    "/js/bundle/pos_receipt.1db6ca7d2caaa5e3.js": "/js/bundle/pos_receipt.1db6ca7d2caaa5e3.js",
    "/js/bundle/payment_gateway.1db6ca7d2caaa5e3.js": "/js/bundle/payment_gateway.1db6ca7d2caaa5e3.js",
    "/js/bundle/mail_settings.1db6ca7d2caaa5e3.js": "/js/bundle/mail_settings.1db6ca7d2caaa5e3.js",
    "/js/bundle/module_settings.1db6ca7d2caaa5e3.js": "/js/bundle/module_settings.1db6ca7d2caaa5e3.js",
    "/js/bundle/update_settings.1db6ca7d2caaa5e3.js": "/js/bundle/update_settings.1db6ca7d2caaa5e3.js",
    "/js/bundle/Currencies.1db6ca7d2caaa5e3.js": "/js/bundle/Currencies.1db6ca7d2caaa5e3.js",
    "/js/bundle/Backup.1db6ca7d2caaa5e3.js": "/js/bundle/Backup.1db6ca7d2caaa5e3.js",
    "/js/bundle/Warehouses.1db6ca7d2caaa5e3.js": "/js/bundle/Warehouses.1db6ca7d2caaa5e3.js",
    "/js/bundle/System_settings.1db6ca7d2caaa5e3.js": "/js/bundle/System_settings.1db6ca7d2caaa5e3.js",
    "/js/bundle/login_devices.1db6ca7d2caaa5e3.js": "/js/bundle/login_devices.1db6ca7d2caaa5e3.js",
    "/js/bundle/custom_fields.1db6ca7d2caaa5e3.js": "/js/bundle/custom_fields.1db6ca7d2caaa5e3.js",
    "/js/bundle/woocommerce.1db6ca7d2caaa5e3.js": "/js/bundle/woocommerce.1db6ca7d2caaa5e3.js",
    "/js/bundle/payments_purchases.1db6ca7d2caaa5e3.js": "/js/bundle/payments_purchases.1db6ca7d2caaa5e3.js",
    "/js/bundle/payments_sales.1db6ca7d2caaa5e3.js": "/js/bundle/payments_sales.1db6ca7d2caaa5e3.js",
    "/js/bundle/payments_purchases_returns.1db6ca7d2caaa5e3.js": "/js/bundle/payments_purchases_returns.1db6ca7d2caaa5e3.js",
    "/js/bundle/payments_sales_returns.1db6ca7d2caaa5e3.js": "/js/bundle/payments_sales_returns.1db6ca7d2caaa5e3.js",
    "/js/bundle/Inactive_Customers_Report.1db6ca7d2caaa5e3.js": "/js/bundle/Inactive_Customers_Report.1db6ca7d2caaa5e3.js",
    "/js/bundle/Zero_Sales_Products_Report.1db6ca7d2caaa5e3.js": "/js/bundle/Zero_Sales_Products_Report.1db6ca7d2caaa5e3.js",
    "/js/bundle/Dead_Stock_Report.1db6ca7d2caaa5e3.js": "/js/bundle/Dead_Stock_Report.1db6ca7d2caaa5e3.js",
    "/js/bundle/Stock_Aging_Report.1db6ca7d2caaa5e3.js": "/js/bundle/Stock_Aging_Report.1db6ca7d2caaa5e3.js",
    "/js/bundle/Stock_Transfer_Report.1db6ca7d2caaa5e3.js": "/js/bundle/Stock_Transfer_Report.1db6ca7d2caaa5e3.js",
    "/js/bundle/Top_Suppliers_Report.1db6ca7d2caaa5e3.js": "/js/bundle/Top_Suppliers_Report.1db6ca7d2caaa5e3.js",
    "/js/bundle/Draft_Invoices_Report.1db6ca7d2caaa5e3.js": "/js/bundle/Draft_Invoices_Report.1db6ca7d2caaa5e3.js",
    "/js/bundle/Discount_Summary_Report.1db6ca7d2caaa5e3.js": "/js/bundle/Discount_Summary_Report.1db6ca7d2caaa5e3.js",
    "/js/bundle/Customer_Loyalty_Points_Report.1db6ca7d2caaa5e3.js": "/js/bundle/Customer_Loyalty_Points_Report.1db6ca7d2caaa5e3.js",
    "/js/bundle/Tax_Summary_Report.1db6ca7d2caaa5e3.js": "/js/bundle/Tax_Summary_Report.1db6ca7d2caaa5e3.js",
    "/js/bundle/cash_flow_report.1db6ca7d2caaa5e3.js": "/js/bundle/cash_flow_report.1db6ca7d2caaa5e3.js",
    "/js/bundle/report_transactions.1db6ca7d2caaa5e3.js": "/js/bundle/report_transactions.1db6ca7d2caaa5e3.js",
    "/js/bundle/seller_report.1db6ca7d2caaa5e3.js": "/js/bundle/seller_report.1db6ca7d2caaa5e3.js",
    "/js/bundle/report_sales_by_category.1db6ca7d2caaa5e3.js": "/js/bundle/report_sales_by_category.1db6ca7d2caaa5e3.js",
    "/js/bundle/report_sales_by_brand.1db6ca7d2caaa5e3.js": "/js/bundle/report_sales_by_brand.1db6ca7d2caaa5e3.js",
    "/js/bundle/profit_and_loss.1db6ca7d2caaa5e3.js": "/js/bundle/profit_and_loss.1db6ca7d2caaa5e3.js",
    "/js/bundle/inventory_valuation_summary.1db6ca7d2caaa5e3.js": "/js/bundle/inventory_valuation_summary.1db6ca7d2caaa5e3.js",
    "/js/bundle/expenses_report.1db6ca7d2caaa5e3.js": "/js/bundle/expenses_report.1db6ca7d2caaa5e3.js",
    "/js/bundle/deposits_report.1db6ca7d2caaa5e3.js": "/js/bundle/deposits_report.1db6ca7d2caaa5e3.js",
    "/js/bundle/return_ratio_report.1db6ca7d2caaa5e3.js": "/js/bundle/return_ratio_report.1db6ca7d2caaa5e3.js",
    "/js/bundle/negative_stock_report.1db6ca7d2caaa5e3.js": "/js/bundle/negative_stock_report.1db6ca7d2caaa5e3.js",
    "/js/bundle/quantity_alerts.1db6ca7d2caaa5e3.js": "/js/bundle/quantity_alerts.1db6ca7d2caaa5e3.js",
    "/js/bundle/warehouse_report.1db6ca7d2caaa5e3.js": "/js/bundle/warehouse_report.1db6ca7d2caaa5e3.js",
    "/js/bundle/sales_report.1db6ca7d2caaa5e3.js": "/js/bundle/sales_report.1db6ca7d2caaa5e3.js",
    "/js/bundle/product_sales_report.1db6ca7d2caaa5e3.js": "/js/bundle/product_sales_report.1db6ca7d2caaa5e3.js",
    "/js/bundle/purchase_report.1db6ca7d2caaa5e3.js": "/js/bundle/purchase_report.1db6ca7d2caaa5e3.js",
    "/js/bundle/product_purchases_report.1db6ca7d2caaa5e3.js": "/js/bundle/product_purchases_report.1db6ca7d2caaa5e3.js",
    "/js/bundle/customers_report.1db6ca7d2caaa5e3.js": "/js/bundle/customers_report.1db6ca7d2caaa5e3.js",
    "/js/bundle/detail_customer_report.1db6ca7d2caaa5e3.js": "/js/bundle/detail_customer_report.1db6ca7d2caaa5e3.js",
    "/js/bundle/providers_report.1db6ca7d2caaa5e3.js": "/js/bundle/providers_report.1db6ca7d2caaa5e3.js",
    "/js/bundle/detail_supplier_report.1db6ca7d2caaa5e3.js": "/js/bundle/detail_supplier_report.1db6ca7d2caaa5e3.js",
    "/js/bundle/top_selling_products.1db6ca7d2caaa5e3.js": "/js/bundle/top_selling_products.1db6ca7d2caaa5e3.js",
    "/js/bundle/product_report.1db6ca7d2caaa5e3.js": "/js/bundle/product_report.1db6ca7d2caaa5e3.js",
    "/js/bundle/detail_product_report.1db6ca7d2caaa5e3.js": "/js/bundle/detail_product_report.1db6ca7d2caaa5e3.js",
    "/js/bundle/top_customers.1db6ca7d2caaa5e3.js": "/js/bundle/top_customers.1db6ca7d2caaa5e3.js",
    "/js/bundle/stock_report.1db6ca7d2caaa5e3.js": "/js/bundle/stock_report.1db6ca7d2caaa5e3.js",
    "/js/bundle/detail_stock_report.1db6ca7d2caaa5e3.js": "/js/bundle/detail_stock_report.1db6ca7d2caaa5e3.js",
    "/js/bundle/users_report.1db6ca7d2caaa5e3.js": "/js/bundle/users_report.1db6ca7d2caaa5e3.js",
    "/js/bundle/detail_user_report.1db6ca7d2caaa5e3.js": "/js/bundle/detail_user_report.1db6ca7d2caaa5e3.js",
    "/js/bundle/login_activity_report.1db6ca7d2caaa5e3.js": "/js/bundle/login_activity_report.1db6ca7d2caaa5e3.js",
    "/js/bundle/report_error_logs.1db6ca7d2caaa5e3.js": "/js/bundle/report_error_logs.1db6ca7d2caaa5e3.js",
    "/js/bundle/cash_register_report.1db6ca7d2caaa5e3.js": "/js/bundle/cash_register_report.1db6ca7d2caaa5e3.js",
    "/js/bundle/Attendance_Report.1db6ca7d2caaa5e3.js": "/js/bundle/Attendance_Report.1db6ca7d2caaa5e3.js",
    "/js/bundle/Service_Jobs_Report.1db6ca7d2caaa5e3.js": "/js/bundle/Service_Jobs_Report.1db6ca7d2caaa5e3.js",
    "/js/bundle/Checklist_Completion_Report.1db6ca7d2caaa5e3.js": "/js/bundle/Checklist_Completion_Report.1db6ca7d2caaa5e3.js",
    "/js/bundle/Customer_Maintenance_History_Report.1db6ca7d2caaa5e3.js": "/js/bundle/Customer_Maintenance_History_Report.1db6ca7d2caaa5e3.js",
    "/js/bundle/profile.1db6ca7d2caaa5e3.js": "/js/bundle/profile.1db6ca7d2caaa5e3.js",
    "/js/bundle/crm.1db6ca7d2caaa5e3.js": "/js/bundle/crm.1db6ca7d2caaa5e3.js",
    "/js/bundle/crm-dashboard.1db6ca7d2caaa5e3.js": "/js/bundle/crm-dashboard.1db6ca7d2caaa5e3.js",
    "/js/bundle/crm-pipelines.1db6ca7d2caaa5e3.js": "/js/bundle/crm-pipelines.1db6ca7d2caaa5e3.js",
    "/js/bundle/crm-pipeline-edit.1db6ca7d2caaa5e3.js": "/js/bundle/crm-pipeline-edit.1db6ca7d2caaa5e3.js",
    "/js/bundle/crm-pipeline-stages.1db6ca7d2caaa5e3.js": "/js/bundle/crm-pipeline-stages.1db6ca7d2caaa5e3.js",
    "/js/bundle/crm-deals.1db6ca7d2caaa5e3.js": "/js/bundle/crm-deals.1db6ca7d2caaa5e3.js",
    "/js/bundle/crm-deal-edit.1db6ca7d2caaa5e3.js": "/js/bundle/crm-deal-edit.1db6ca7d2caaa5e3.js",
    "/js/bundle/crm-deal-detail.1db6ca7d2caaa5e3.js": "/js/bundle/crm-deal-detail.1db6ca7d2caaa5e3.js",
    "/js/bundle/crm-followups.1db6ca7d2caaa5e3.js": "/js/bundle/crm-followups.1db6ca7d2caaa5e3.js",
    "/js/bundle/crm-followup-edit.1db6ca7d2caaa5e3.js": "/js/bundle/crm-followup-edit.1db6ca7d2caaa5e3.js",
    "/js/bundle/crm-followup-detail.1db6ca7d2caaa5e3.js": "/js/bundle/crm-followup-detail.1db6ca7d2caaa5e3.js",
    "/js/bundle/crm-forms.1db6ca7d2caaa5e3.js": "/js/bundle/crm-forms.1db6ca7d2caaa5e3.js",
    "/js/bundle/crm-form-builder.1db6ca7d2caaa5e3.js": "/js/bundle/crm-form-builder.1db6ca7d2caaa5e3.js",
    "/js/bundle/crm-form-submissions.1db6ca7d2caaa5e3.js": "/js/bundle/crm-form-submissions.1db6ca7d2caaa5e3.js",
    "/js/bundle/crm-submission-detail.1db6ca7d2caaa5e3.js": "/js/bundle/crm-submission-detail.1db6ca7d2caaa5e3.js",
    "/js/bundle/crm-contacts.1db6ca7d2caaa5e3.js": "/js/bundle/crm-contacts.1db6ca7d2caaa5e3.js",
    "/js/bundle/crm-contact-detail.1db6ca7d2caaa5e3.js": "/js/bundle/crm-contact-detail.1db6ca7d2caaa5e3.js",
    "/js/bundle/crm-groups.1db6ca7d2caaa5e3.js": "/js/bundle/crm-groups.1db6ca7d2caaa5e3.js",
    "/js/bundle/crm-tags.1db6ca7d2caaa5e3.js": "/js/bundle/crm-tags.1db6ca7d2caaa5e3.js",
    "/js/bundle/pos.1db6ca7d2caaa5e3.js": "/js/bundle/pos.1db6ca7d2caaa5e3.js",
    "/js/bundle/NotFound.1db6ca7d2caaa5e3.js": "/js/bundle/NotFound.1db6ca7d2caaa5e3.js",
    "/js/bundle/not_authorize.1db6ca7d2caaa5e3.js": "/js/bundle/not_authorize.1db6ca7d2caaa5e3.js",
    "/js/bundle/largeSidebar.1db6ca7d2caaa5e3.js": "/js/bundle/largeSidebar.1db6ca7d2caaa5e3.js",
    "/js/bundle/customizer.1db6ca7d2caaa5e3.js": "/js/bundle/customizer.1db6ca7d2caaa5e3.js",
    "/js/bundle/vue-perfect-scrollbar.1db6ca7d2caaa5e3.js": "/js/bundle/vue-perfect-scrollbar.1db6ca7d2caaa5e3.js",
    "/js/bundle/woo-settings-tab.1db6ca7d2caaa5e3.js": "/js/bundle/woo-settings-tab.1db6ca7d2caaa5e3.js",
    "/js/bundle/woo-products-tab.1db6ca7d2caaa5e3.js": "/js/bundle/woo-products-tab.1db6ca7d2caaa5e3.js",
    "/js/bundle/woo-stock-tab.1db6ca7d2caaa5e3.js": "/js/bundle/woo-stock-tab.1db6ca7d2caaa5e3.js",
    "/js/bundle/woo-categories-tab.1db6ca7d2caaa5e3.js": "/js/bundle/woo-categories-tab.1db6ca7d2caaa5e3.js",
    "/js/bundle/woo-logs-tab.1db6ca7d2caaa5e3.js": "/js/bundle/woo-logs-tab.1db6ca7d2caaa5e3.js",
    "/js/bundle/woo-status-tab.1db6ca7d2caaa5e3.js": "/js/bundle/woo-status-tab.1db6ca7d2caaa5e3.js"
}
